m_crawler/__init__.py
m_crawler/__init__.pyi
m_crawler/config.py
m_crawler/config.pyi
m_crawler/engine/__init__.py
m_crawler/engine/__init__.pyi
m_crawler/engine/abstract_engine.py
m_crawler/engine/abstract_engine.pyi
m_crawler/engine/abstract_request.py
m_crawler/engine/abstract_request.pyi
m_crawler/engine/abstract_response.py
m_crawler/engine/abstract_response.pyi
m_crawler/engine/crawler.py
m_crawler/engine/crawler.pyi
m_crawler/engine/playwright_engine.py
m_crawler/engine/playwright_engine.pyi
m_crawler/engine/request.py
m_crawler/engine/request.pyi
m_crawler/engine/response.py
m_crawler/engine/response.pyi
m_crawler/pipeline/__init__.py
m_crawler/pipeline/__init__.pyi
m_crawler/pipeline/abstracy_pipeline.py
m_crawler/pipeline/abstracy_pipeline.pyi
m_crawler/utils/__init__.py
m_crawler/utils/__init__.pyi
m_crawler/utils/count_down.py
m_crawler/utils/count_down.pyi
m_crawler/utils/crawler_exception.py
m_crawler/utils/crawler_exception.pyi
m_crawler/utils/parser.py
m_crawler/utils/parser.pyi
m_crawler-0.1.22.dist-info/METADATA
m_crawler-0.1.22.dist-info/WHEEL
m_crawler-0.1.22.dist-info/top_level.txt
m_crawler-0.1.22.dist-info/RECORD
