Metadata-Version: 2.4
Name: m_crawler
Version: 0.1.22
Summary: A base crawler
Requires-Python: >=3.11
Requires-Dist: beautifulsoup4>=4.13.4
Requires-Dist: loguru>=0.7.3
Requires-Dist: lxml>=6.0.0
Requires-Dist: pytest-playwright>=0.7.0
